easygraph/__init__.py
easygraph/easy_graph.py
easygraph/jquery.flot.axislabels.js
easygraph/render_output.html
easygraph-0.2.0.dist-info/DESCRIPTION.rst
easygraph-0.2.0.dist-info/METADATA
easygraph-0.2.0.dist-info/RECORD
easygraph-0.2.0.dist-info/WHEEL
easygraph-0.2.0.dist-info/metadata.json
easygraph-0.2.0.dist-info/top_level.txt
easygraph-0.2.0.dist-info/zip-safe
