Metadata-Version: 2.0
Name: easygraph
Version: 0.2.0
Summary: Easily turn your python data into a flot graph in a static html file.
Home-page: https://github.com/JesseAldridge/easy_graph
Author: Jesse Aldridge
Author-email: JesseAldridge@gmail.com
License: MIT
Keywords: graph graphing plot
Platform: UNKNOWN
